kz/__init__.py
kz/validators/__init__.py
kz/validators/_iin_validator.py
py_kz_validators-0.0.2.dist-info/LICENSE
py_kz_validators-0.0.2.dist-info/METADATA
py_kz_validators-0.0.2.dist-info/WHEEL
py_kz_validators-0.0.2.dist-info/top_level.txt
py_kz_validators-0.0.2.dist-info/RECORD
