Metadata-Version: 2.1
Name: py-kz-validators
Version: 0.0.2
Summary: A collection of Python validators for various Kazakhstani identification numbers, such as the Individual Identification Number (IIN) and Taxpayer Identification Number (TIN)
Author-email: Talgat Abdraimov <abdraimov.talga@gmail.com>
License: MIT License
Project-URL: homepage, https://github.com/tlgtaa/py-kz-validators
Project-URL: repository, https://github.com/tlgtaa/py-kz-validators.git
Requires-Python: >=3.10
License-File: LICENSE
Provides-Extra: dev
Requires-Dist: black ; extra == 'dev'
Requires-Dist: pytest ; extra == 'dev'
Requires-Dist: pytest-cov ; extra == 'dev'
Requires-Dist: flake8 ; extra == 'dev'
Requires-Dist: flake8-print ; extra == 'dev'
Requires-Dist: flake8-multiline-containers ; extra == 'dev'
Requires-Dist: flake8-builtins ; extra == 'dev'
Requires-Dist: flake8-import-order ; extra == 'dev'
Requires-Dist: flake8-commas ; extra == 'dev'
Requires-Dist: flake8-quotes ; extra == 'dev'
